{
  "minecraft:recipes/decorations/torch": {
    "criteria": {
      "has_stone_pickaxe": "2018-12-06 15:44:27 +0000"
    },
    "done": true
  },
  "minecraft:recipes/transportation/acacia_boat": {
    "criteria": {
      "in_water": "2018-12-06 15:54:04 +0000"
    },
    "done": true
  },
  "minecraft:recipes/transportation/oak_boat": {
    "criteria": {
      "in_water": "2018-12-06 15:54:04 +0000"
    },
    "done": true
  },
  "minecraft:recipes/building_blocks/andesite": {
    "criteria": {
      "has_stone": "2018-12-07 11:46:20 +0000"
    },
    "done": true
  },
  "minecraft:recipes/transportation/dark_oak_boat": {
    "criteria": {
      "in_water": "2018-12-06 15:54:04 +0000"
    },
    "done": true
  },
  "minecraft:husbandry/root": {
    "criteria": {
      "consumed_item": "2018-12-06 16:28:21 +0000"
    },
    "done": true
  },
  "minecraft:recipes/transportation/birch_boat": {
    "criteria": {
      "in_water": "2018-12-06 15:54:04 +0000"
    },
    "done": true
  },
  "minecraft:recipes/transportation/jungle_boat": {
    "criteria": {
      "in_water": "2018-12-06 15:54:04 +0000"
    },
    "done": true
  },
  "minecraft:recipes/building_blocks/polished_diorite": {
    "criteria": {
      "has_stone": "2018-12-07 11:46:20 +0000"
    },
    "done": true
  },
  "minecraft:story/upgrade_tools": {
    "criteria": {
      "stone_pickaxe": "2018-12-06 15:44:27 +0000"
    },
    "done": true
  },
  "minecraft:recipes/transportation/spruce_boat": {
    "criteria": {
      "in_water": "2018-12-06 15:54:04 +0000"
    },
    "done": true
  },
  "minecraft:adventure/adventuring_time": {
    "criteria": {
      "minecraft:forest": "2018-12-06 15:45:27 +0000",
      "minecraft:snowy_tundra": "2018-12-06 15:44:27 +0000"
    },
    "done": false
  }
}