{"stats":{"minecraft:used":{"minecraft:stone_brick_stairs":49,"minecraft:trident":9,"minecraft:brown_stained_glass_pane":15,"minecraft:red_stained_glass_pane":41,"minecraft:quartz_pillar":53,"minecraft:light_gray_stained_glass_pane":9,"minecraft:red_wool":5,"minecraft:quartz_slab":2,"minecraft:black_stained_glass_pane":46,"minecraft:red_stained_glass":3,"minecraft:grass_block":30,"minecraft:red_nether_bricks":23,"minecraft:quartz_block":472,"minecraft:pink_stained_glass":1,"minecraft:chiseled_quartz_block":42,"minecraft:red_terracotta":4,"minecraft:smooth_quartz":3,"minecraft:infested_stone_bricks":32,"minecraft:orange_stained_glass_pane":7,"minecraft:green_stained_glass_pane":17,"minecraft:quartz_stairs":458,"minecraft:pink_stained_glass_pane":7},"minecraft:custom":{"minecraft:time_since_rest":260639,"minecraft:crouch_one_cm":1201,"minecraft:play_one_minute":260639,"minecraft:sprint_one_cm":51163,"minecraft:walk_one_cm":156153,"minecraft:sneak_time":2437,"minecraft:jump":359,"minecraft:leave_game":1,"minecraft:time_since_death":260639,"minecraft:fly_one_cm":1457109}},"DataVersion":1631}