{"stats":{"minecraft:custom":{"minecraft:jump":3,"minecraft:time_since_rest":11749,"minecraft:crouch_one_cm":180,"minecraft:play_one_minute":11749,"minecraft:leave_game":2,"minecraft:time_since_death":11749,"minecraft:walk_one_cm":2142,"minecraft:sneak_time":99,"minecraft:fly_one_cm":356797},"minecraft:used":{"minecraft:dark_prismarine":1,"minecraft:infested_stone_bricks":1,"minecraft:stripped_dark_oak_wood":1,"minecraft:black_concrete_powder":1,"minecraft:smooth_quartz":1,"minecraft:black_stained_glass_pane":1,"minecraft:prismarine_bricks":1}},"DataVersion":1631}