{"stats":{"minecraft:dropped":{"minecraft:nether_brick_slab":1,"minecraft:tnt":29,"minecraft:dark_oak_trapdoor":1,"minecraft:wooden_axe":1,"minecraft:quartz_block":2,"minecraft:smooth_quartz":1,"minecraft:stone_shovel":1,"minecraft:cobblestone":1,"minecraft:black_shulker_box":1,"minecraft:acacia_fence_gate":1,"minecraft:stone_slab":1,"minecraft:black_concrete":2,"minecraft:black_stained_glass":1,"minecraft:dark_oak_fence_gate":1,"minecraft:quartz_slab":129},"minecraft:picked_up":{"minecraft:fire_charge":56,"minecraft:redstone_torch":1,"minecraft:white_shulker_box":1},"minecraft:used":{"minecraft:redstone_torch":36,"minecraft:black_terracotta":100,"minecraft:brown_terracotta":4,"minecraft:dark_oak_planks":180,"minecraft:dark_oak_stairs":245,"minecraft:black_wool":20,"minecraft:black_concrete":22,"minecraft:iron_bars":6,"minecraft:cow_spawn_egg":2,"minecraft:cobblestone_stairs":40,"minecraft:birch_fence_gate":1,"minecraft:quartz_pillar":1,"minecraft:villager_spawn_egg":7,"minecraft:dark_oak_log":5,"minecraft:quartz_slab":475,"minecraft:black_stained_glass_pane":6,"minecraft:red_concrete":1678,"minecraft:quartz_block":1375,"minecraft:dark_oak_slab":70,"minecraft:stone_slab":280,"minecraft:red_terracotta":177,"minecraft:black_shulker_box":1,"minecraft:spruce_trapdoor":4,"minecraft:redstone_block":3,"minecraft:smooth_quartz":315,"minecraft:dark_oak_button":4,"minecraft:quartz_stairs":634,"minecraft:cobblestone_slab":15,"minecraft:stone_bricks":1,"minecraft:cracked_stone_bricks":13,"minecraft:coal_block":54,"minecraft:dark_oak_trapdoor":34,"minecraft:redstone_lamp":2,"minecraft:cobblestone":28,"minecraft:black_stained_glass":150,"minecraft:tnt":12,"minecraft:iron_trapdoor":36,"minecraft:jungle_button":1,"minecraft:dark_oak_fence":16,"minecraft:cobblestone_wall":16,"minecraft:glass_pane":6,"minecraft:dark_oak_fence_gate":17,"minecraft:dead_bubble_coral_block":4,"minecraft:white_concrete":2,"minecraft:husk_spawn_egg":2,"minecraft:black_concrete_powder":1,"minecraft:dead_brain_coral_block":17,"minecraft:spruce_log":2},"minecraft:custom":{"minecraft:time_since_rest":791087,"minecraft:sprint_one_cm":11000,"minecraft:walk_one_cm":50864,"minecraft:drop":19,"minecraft:fly_one_cm":10348151,"minecraft:crouch_one_cm":2053,"minecraft:play_one_minute":791087,"minecraft:sneak_time":33305,"minecraft:walk_under_water_one_cm":5198,"minecraft:jump":230,"minecraft:leave_game":16,"minecraft:walk_on_water_one_cm":14956,"minecraft:time_since_death":787248,"minecraft:inspect_dispenser":5}},"DataVersion":1631}