{"stats":{"minecraft:dropped":{"minecraft:red_sandstone_stairs":1,"minecraft:polished_andesite":2},"minecraft:used":{"minecraft:red_sandstone_stairs":3,"minecraft:bedrock":8,"minecraft:glass":26,"minecraft:lever":2,"minecraft:end_stone_bricks":127,"minecraft:purpur_stairs":1,"minecraft:chiseled_sandstone":114,"minecraft:sandstone_stairs":104,"minecraft:quartz_pillar":68,"minecraft:stripped_birch_log":1,"minecraft:grass_block":1,"minecraft:polished_andesite":11,"minecraft:smooth_sandstone":122,"minecraft:sandstone_slab":8,"minecraft:glass_pane":373,"minecraft:sandstone":3,"minecraft:stone":83,"minecraft:cut_sandstone":131,"minecraft:iron_door":16,"minecraft:stripped_birch_wood":75,"minecraft:quartz_stairs":54,"minecraft:gravel":22},"minecraft:custom":{"minecraft:time_since_rest":159962,"minecraft:play_one_minute":159962,"minecraft:crouch_one_cm":541,"minecraft:sprint_one_cm":65828,"minecraft:walk_one_cm":156664,"minecraft:sneak_time":1495,"minecraft:drop":3,"minecraft:jump":142,"minecraft:leave_game":1,"minecraft:time_since_death":159962,"minecraft:fly_one_cm":1675264}},"DataVersion":1631}