{"stats":{"minecraft:crafted":{"minecraft:leather_chestplate":1},"minecraft:custom":{"minecraft:time_since_rest":253220,"minecraft:interact_with_furnace":5,"minecraft:sprint_one_cm":160932,"minecraft:walk_one_cm":297295,"minecraft:drop":7,"minecraft:interact_with_crafting_table":1,"minecraft:swim_one_cm":8832,"minecraft:fly_one_cm":1628838,"minecraft:open_chest":4,"minecraft:play_one_minute":253220,"minecraft:crouch_one_cm":5064,"minecraft:sneak_time":4555,"minecraft:walk_under_water_one_cm":74281,"minecraft:aviate_one_cm":325079,"minecraft:jump":983,"minecraft:leave_game":8,"minecraft:time_since_death":253220,"minecraft:walk_on_water_one_cm":27043,"minecraft:climb_one_cm":2288},"minecraft:dropped":{"minecraft:bricks":1,"minecraft:wooden_axe":1,"minecraft:stripped_birch_log":1,"minecraft:stone_bricks":1,"minecraft:spruce_log":2,"minecraft:armor_stand":1},"minecraft:used":{"minecraft:oak_fence":317,"minecraft:water_bucket":821,"minecraft:trident":6,"minecraft:bricks":947,"minecraft:villager_spawn_egg":3,"minecraft:spruce_door":5,"minecraft:armor_stand":6,"minecraft:brick_stairs":69,"minecraft:ladder":45,"minecraft:ender_pearl":44,"minecraft:chest":34,"minecraft:stone":111,"minecraft:stone_bricks":386,"minecraft:torch":51,"minecraft:bow":8,"minecraft:potion":4,"minecraft:crafting_table":6,"minecraft:furnace":38,"minecraft:brick_slab":338,"minecraft:spruce_stairs":168,"minecraft:gray_bed":31,"minecraft:acacia_fence":79,"minecraft:acacia_leaves":12,"minecraft:glass_pane":88,"minecraft:spruce_log":366},"minecraft:mined":{"minecraft:gray_bed":7}},"DataVersion":1631}