{"stats":{"minecraft:dropped":{"minecraft:oak_fence":1,"minecraft:oak_slab":1,"minecraft:rail":1,"minecraft:glowstone":1},"minecraft:used":{"minecraft:oak_door":40,"minecraft:oak_trapdoor":5,"minecraft:oak_fence":126,"minecraft:glass":10,"minecraft:lever":11,"minecraft:water_bucket":3,"minecraft:glowstone":40,"minecraft:rail":9,"minecraft:bookshelf":26,"minecraft:oak_slab":87,"minecraft:hopper":1,"minecraft:minecart":5,"minecraft:sign":18,"minecraft:gray_concrete":1859,"minecraft:painting":58},"minecraft:custom":{"minecraft:time_since_rest":250705,"minecraft:play_one_minute":250705,"minecraft:sprint_one_cm":5754,"minecraft:walk_one_cm":306201,"minecraft:sneak_time":5,"minecraft:walk_under_water_one_cm":67,"minecraft:drop":4,"minecraft:jump":267,"minecraft:inspect_hopper":4,"minecraft:leave_game":4,"minecraft:walk_on_water_one_cm":3745,"minecraft:time_since_death":250705,"minecraft:fly_one_cm":961497}},"DataVersion":1631}