{"stats":{"minecraft:picked_up":{"minecraft:ladder":2,"minecraft:wheat_seeds":1,"minecraft:black_banner":3},"minecraft:dropped":{"minecraft:gravel":1,"minecraft:red_concrete":1,"minecraft:furnace":1,"minecraft:bricks":1,"minecraft:stripped_spruce_log":1,"minecraft:stone_axe":1,"minecraft:diamond_block":1,"minecraft:golden_chestplate":1,"minecraft:stone_sword":1,"minecraft:chiseled_quartz_block":2,"minecraft:gray_banner":1,"minecraft:jukebox":1,"minecraft:diamond":128,"minecraft:crafting_table":2,"minecraft:lime_wool":2,"minecraft:sandstone_slab":1,"minecraft:stone_shovel":1,"minecraft:dead_bubble_coral_block":1,"minecraft:cobblestone":1,"minecraft:blue_concrete_powder":1,"minecraft:green_concrete":1,"minecraft:quartz_pillar":2,"minecraft:nether_brick_fence":1,"minecraft:dead_horn_coral_block":2,"minecraft:spruce_door":1,"minecraft:white_bed":1,"minecraft:black_banner":1,"minecraft:grass_block":4,"minecraft:dead_fire_coral_block":1,"minecraft:sign":4,"minecraft:snow":1,"minecraft:sea_lantern":2,"minecraft:brown_concrete_powder":1,"minecraft:flower_pot":1,"minecraft:brick_stairs":1,"minecraft:milk_bucket":1,"minecraft:heavy_weighted_pressure_plate":1,"minecraft:torch":1,"minecraft:black_stained_glass_pane":1,"minecraft:oak_wood":2,"minecraft:dark_oak_trapdoor":1,"minecraft:light_blue_wool":1,"minecraft:wooden_axe":7,"minecraft:quartz_block":1,"minecraft:quartz_stairs":2,"minecraft:smooth_quartz":2,"minecraft:cut_sandstone":3,"minecraft:chest":1,"minecraft:potion":4,"minecraft:purple_concrete_powder":1,"minecraft:stone_pressure_plate":1,"minecraft:oak_stairs":1,"minecraft:magenta_concrete_powder":1,"minecraft:painting":2,"minecraft:orange_concrete_powder":1,"minecraft:beacon":1,"minecraft:sand":1,"minecraft:glass":3,"minecraft:stone_pickaxe":1,"minecraft:dead_brain_coral_block":2,"minecraft:brick_slab":1,"minecraft:dark_prismarine":1,"minecraft:stone_brick_stairs":1,"minecraft:trapped_chest":1,"minecraft:white_stained_glass":1,"minecraft:light_gray_concrete_powder":1,"minecraft:splash_potion":2,"minecraft:quartz_slab":2},"minecraft:custom":{"minecraft:interact_with_furnace":7,"minecraft:interact_with_crafting_table":4,"minecraft:play_one_minute":1246629,"minecraft:pot_flower":24,"minecraft:leave_game":24,"minecraft:time_since_death":1246629,"minecraft:time_since_rest":1246629,"minecraft:sprint_one_cm":540523,"minecraft:walk_one_cm":1115731,"minecraft:drop":101,"minecraft:interact_with_beacon":1,"minecraft:swim_one_cm":20281,"minecraft:fly_one_cm":10235556,"minecraft:open_chest":1,"minecraft:crouch_one_cm":6242,"minecraft:sneak_time":3477,"minecraft:walk_under_water_one_cm":64481,"minecraft:aviate_one_cm":1995688,"minecraft:jump":2415,"minecraft:walk_on_water_one_cm":67882,"minecraft:inspect_dispenser":5},"minecraft:crafted":{"minecraft:black_banner":2,"minecraft:blue_banner":2},"minecraft:used":{"minecraft:end_rod":25,"minecraft:oak_fence":135,"minecraft:stripped_acacia_wood":1,"minecraft:oak_trapdoor":35,"minecraft:nether_brick_fence":63,"minecraft:water_bucket":1,"minecraft:jungle_leaves":243,"minecraft:iron_bars":62,"minecraft:enchanting_table":1,"minecraft:pink_tulip":12,"minecraft:spruce_door":100,"minecraft:white_tulip":17,"minecraft:oak_planks":104,"minecraft:armor_stand":31,"minecraft:dispenser":1,"minecraft:lime_wool":7,"minecraft:ladder":53,"minecraft:orange_tulip":18,"minecraft:chest":2,"minecraft:stone":25,"minecraft:cut_sandstone":1434,"minecraft:redstone_block":2,"minecraft:beacon":1,"minecraft:quartz_stairs":367,"minecraft:player_head":4,"minecraft:spruce_leaves":887,"minecraft:torch":19,"minecraft:dark_oak_trapdoor":2,"minecraft:diamond_block":35,"minecraft:sand":26,"minecraft:anvil":1,"minecraft:crafting_table":3,"minecraft:brick_slab":777,"minecraft:light_blue_wool":68,"minecraft:black_banner":111,"minecraft:white_bed":4,"minecraft:chiseled_quartz_block":508,"minecraft:oak_wood":24,"minecraft:dark_oak_fence_gate":1,"minecraft:painting":27,"minecraft:jungle_trapdoor":38,"minecraft:cyan_wool":6,"minecraft:cake":34,"minecraft:stripped_spruce_log":114,"minecraft:dark_oak_door":7,"minecraft:milk_bucket":4,"minecraft:birch_door":25,"minecraft:glass":691,"minecraft:dark_prismarine":1,"minecraft:stone_brick_slab":125,"minecraft:flower_pot":28,"minecraft:lever":1,"minecraft:sea_lantern":102,"minecraft:bookshelf":154,"minecraft:bricks":203,"minecraft:quartz_pillar":244,"minecraft:red_tulip":15,"minecraft:black_stained_glass_pane":13,"minecraft:heavy_weighted_pressure_plate":64,"minecraft:quartz_slab":1341,"minecraft:spruce_wood":4,"minecraft:iron_block":5,"minecraft:grass_block":346,"minecraft:oak_stairs":30,"minecraft:brick_stairs":1136,"minecraft:sign":30,"minecraft:stone_slab":142,"minecraft:smooth_quartz":1570,"minecraft:iron_door":7,"minecraft:gravel":87,"minecraft:stone_brick_stairs":285,"minecraft:stone_bricks":30,"minecraft:item_frame":11,"minecraft:potion":17,"minecraft:snow":35,"minecraft:cobblestone":17,"minecraft:iron_trapdoor":48,"minecraft:furnace":43,"minecraft:dark_oak_fence":179,"minecraft:andesite":9,"minecraft:green_concrete_powder":3,"minecraft:white_stained_glass":153,"minecraft:sandstone_slab":1,"minecraft:trapped_chest":2,"minecraft:stone_pressure_plate":3,"minecraft:jukebox":2,"minecraft:splash_potion":162}},"DataVersion":1631}