{"stats":{"minecraft:picked_up":{"minecraft:diamond_shovel":1},"minecraft:custom":{"minecraft:time_since_rest":277052,"minecraft:play_one_minute":277052,"minecraft:crouch_one_cm":1035,"minecraft:sprint_one_cm":428562,"minecraft:walk_one_cm":717525,"minecraft:sneak_time":379,"minecraft:drop":26,"minecraft:jump":1406,"minecraft:leave_game":4,"minecraft:time_since_death":277052,"minecraft:fly_one_cm":1302306},"minecraft:used":{"minecraft:coal_block":805,"minecraft:dirt":15,"minecraft:potion":2,"minecraft:bow":31,"minecraft:oak_sapling":4,"minecraft:grass_block":4048,"minecraft:birch_sapling":5,"minecraft:yellow_carpet":70,"minecraft:ender_pearl":38,"minecraft:stone":11,"minecraft:bone_meal":16},"minecraft:dropped":{"minecraft:potion":1,"minecraft:fire_charge":1,"minecraft:diamond_sword":2,"minecraft:dirt":1,"minecraft:oak_planks":1,"minecraft:stone_axe":1,"minecraft:diamond_shovel":2,"minecraft:diamond_boots":1,"minecraft:stone":1,"minecraft:arrow":1,"minecraft:bow":1,"minecraft:diamond_axe":1,"minecraft:stone_pickaxe":1,"minecraft:stone_sword":1,"minecraft:ender_pearl":1,"minecraft:grass_block":5,"minecraft:dark_oak_sapling":2,"minecraft:coal_block":1,"minecraft:lime_wool":1,"minecraft:stone_shovel":1}},"DataVersion":1631}