{"stats":{"minecraft:dropped":{"minecraft:smooth_stone":16,"minecraft:stone_brick_stairs":3,"minecraft:polished_andesite":133},"minecraft:custom":{"minecraft:jump":130,"minecraft:time_since_rest":398191,"minecraft:play_one_minute":398191,"minecraft:leave_game":5,"minecraft:sprint_one_cm":820,"minecraft:time_since_death":398191,"minecraft:walk_one_cm":116476,"minecraft:sneak_time":78,"minecraft:drop":25,"minecraft:fly_one_cm":597014},"minecraft:used":{"minecraft:quartz_block":1,"minecraft:white_concrete":583,"minecraft:firework_rocket":6,"minecraft:smooth_quartz":2,"minecraft:smooth_stone":1411,"minecraft:stone_brick_stairs":5,"minecraft:stone_shovel":1}},"DataVersion":1631}