{"stats":{"minecraft:used":{"minecraft:stone_bricks":66,"minecraft:stone_brick_slab":56,"minecraft:water_bucket":5,"minecraft:stone":2,"minecraft:polished_diorite":83,"minecraft:stone_brick_stairs":18},"minecraft:custom":{"minecraft:jump":66,"minecraft:time_since_rest":21684,"minecraft:crouch_one_cm":11,"minecraft:play_one_minute":21684,"minecraft:walk_on_water_one_cm":2545,"minecraft:sprint_one_cm":10612,"minecraft:time_since_death":21684,"minecraft:walk_one_cm":30371,"minecraft:sneak_time":114,"minecraft:walk_under_water_one_cm":5055,"minecraft:swim_one_cm":917,"minecraft:fly_one_cm":177129}},"DataVersion":1631}