{"stats":{"minecraft:dropped":{"minecraft:quartz_block":1},"minecraft:crafted":{"minecraft:light_gray_banner":5},"minecraft:picked_up":{"minecraft:torch":2},"minecraft:used":{"minecraft:birch_fence":21,"minecraft:dark_prismarine":2,"minecraft:dead_fire_coral_fan":1,"minecraft:stone_brick_slab":300,"minecraft:dark_oak_stairs":8,"minecraft:nether_brick_fence":23,"minecraft:water_bucket":3,"minecraft:end_rod":22,"minecraft:sea_lantern":2,"minecraft:black_concrete":204,"minecraft:iron_bars":143,"minecraft:bricks":55,"minecraft:quartz_pillar":473,"minecraft:dead_fire_coral":5,"minecraft:light_gray_concrete":28,"minecraft:quartz_slab":1617,"minecraft:black_stained_glass_pane":9,"minecraft:grass_block":139,"minecraft:dead_tube_coral_fan":1,"minecraft:polished_andesite":437,"minecraft:string":3,"minecraft:dead_brain_coral":7,"minecraft:oak_planks":42,"minecraft:quartz_block":3057,"minecraft:black_carpet":75,"minecraft:sign":9,"minecraft:white_glazed_terracotta":7,"minecraft:stone_slab":226,"minecraft:stone":28,"minecraft:polished_granite":7,"minecraft:dark_oak_slab":139,"minecraft:quartz_stairs":541,"minecraft:player_head":31,"minecraft:stone_brick_stairs":516,"minecraft:stone_bricks":186,"minecraft:item_frame":3,"minecraft:yellow_concrete_powder":1,"minecraft:dead_horn_coral":49,"minecraft:chiseled_stone_bricks":1,"minecraft:torch":17,"minecraft:glowstone":20,"minecraft:coal_block":127,"minecraft:light_gray_banner":34,"minecraft:potion":6,"minecraft:black_stained_glass":12,"minecraft:gray_glazed_terracotta":4,"minecraft:dead_horn_coral_fan":6,"minecraft:crafting_table":1,"minecraft:skeleton_skull":4,"minecraft:light_gray_glazed_terracotta":165,"minecraft:cobblestone_wall":19,"minecraft:light_gray_concrete_powder":8,"minecraft:glass_pane":44,"minecraft:nether_brick_slab":71,"minecraft:dead_tube_coral":2,"minecraft:dead_bubble_coral":1,"minecraft:chiseled_quartz_block":163,"minecraft:gray_concrete":382,"minecraft:dead_bubble_coral_block":22,"minecraft:dead_brain_coral_fan":1,"minecraft:nether_brick_stairs":96,"minecraft:smooth_stone":44,"minecraft:dead_bubble_coral_fan":1,"minecraft:stripped_spruce_wood":18,"minecraft:polished_diorite":16},"minecraft:custom":{"minecraft:time_since_rest":100156,"minecraft:sprint_one_cm":153901,"minecraft:walk_one_cm":282959,"minecraft:drop":1,"minecraft:swim_one_cm":3129,"minecraft:interact_with_crafting_table":2,"minecraft:fly_one_cm":7565155,"minecraft:play_one_minute":716705,"minecraft:crouch_one_cm":31455,"minecraft:deaths":1,"minecraft:sneak_time":23110,"minecraft:walk_under_water_one_cm":1075,"minecraft:jump":931,"minecraft:leave_game":25,"minecraft:time_since_death":98004,"minecraft:walk_on_water_one_cm":324}},"DataVersion":1631}