{"stats":{"minecraft:picked_up":{"minecraft:lever":1,"minecraft:oak_pressure_plate":1},"minecraft:custom":{"minecraft:time_since_rest":136387,"minecraft:crouch_one_cm":1430,"minecraft:play_one_minute":136387,"minecraft:sprint_one_cm":36498,"minecraft:open_shulker_box":4,"minecraft:walk_one_cm":387098,"minecraft:sneak_time":2378,"minecraft:walk_under_water_one_cm":3734,"minecraft:jump":118,"minecraft:leave_game":4,"minecraft:walk_on_water_one_cm":146185,"minecraft:time_since_death":136387,"minecraft:climb_one_cm":1101,"minecraft:swim_one_cm":613,"minecraft:fly_one_cm":1336524},"minecraft:used":{"minecraft:stone_brick_stairs":16,"minecraft:light_gray_shulker_box":14,"minecraft:oak_log":26,"minecraft:oak_fence":72,"minecraft:yellow_banner":2,"minecraft:lever":5,"minecraft:water_bucket":1203,"minecraft:end_rod":5,"minecraft:sea_lantern":18,"minecraft:glowstone":1,"minecraft:iron_bars":56,"minecraft:anvil":1,"minecraft:villager_spawn_egg":10,"minecraft:red_wool":52,"minecraft:oak_slab":28,"minecraft:armor_stand":1,"minecraft:grass_block":52,"minecraft:ladder":24,"minecraft:cobblestone_wall":270,"minecraft:oak_planks":631,"minecraft:pig_spawn_egg":3,"minecraft:jungle_stairs":18,"minecraft:sponge":4,"minecraft:stripped_oak_log":29,"minecraft:stone":166,"minecraft:dragon_head":2,"minecraft:oak_pressure_plate":4,"minecraft:spruce_fence_gate":1}},"DataVersion":1631}