{"stats":{"minecraft:dropped":{"minecraft:dirt":1,"minecraft:tipped_arrow":64,"minecraft:coarse_dirt":1,"minecraft:wooden_axe":5,"minecraft:acacia_slab":1,"minecraft:red_sandstone":4,"minecraft:stripped_acacia_wood":3,"minecraft:red_sandstone_stairs":2,"minecraft:elytra":1,"minecraft:grass_block":1,"minecraft:splash_potion":1},"minecraft:custom":{"minecraft:time_since_rest":1198110,"minecraft:sprint_one_cm":21138,"minecraft:walk_one_cm":284863,"minecraft:drop":21,"minecraft:fly_one_cm":11457081,"minecraft:play_one_minute":1198110,"minecraft:crouch_one_cm":9803,"minecraft:sneak_time":29855,"minecraft:walk_under_water_one_cm":320,"minecraft:aviate_one_cm":602567,"minecraft:jump":349,"minecraft:time_since_death":1198110,"minecraft:leave_game":19,"minecraft:walk_on_water_one_cm":79},"minecraft:used":{"minecraft:redstone_torch":20,"minecraft:red_sandstone_stairs":1127,"minecraft:sticky_piston":329,"minecraft:stripped_acacia_wood":1689,"minecraft:piston":2,"minecraft:trident":45,"minecraft:acacia_stairs":107,"minecraft:red_sandstone":1450,"minecraft:red_sand":1,"minecraft:chiseled_sandstone":60,"minecraft:sandstone_stairs":850,"minecraft:stripped_acacia_log":15,"minecraft:polished_andesite":34,"minecraft:carved_pumpkin":3,"minecraft:iron_block":9,"minecraft:grass_block":241,"minecraft:red_sandstone_slab":280,"minecraft:redstone":320,"minecraft:slime_block":71,"minecraft:acacia_slab":34,"minecraft:orange_shulker_box":1,"minecraft:chicken_spawn_egg":9,"minecraft:stone":12,"minecraft:white_terracotta":27,"minecraft:sandstone":28,"minecraft:polished_granite":306,"minecraft:cut_sandstone":2,"minecraft:redstone_block":41,"minecraft:cut_red_sandstone":126,"minecraft:gold_ore":1,"minecraft:chiseled_red_sandstone":146,"minecraft:repeater":18,"minecraft:glowstone":28,"minecraft:terracotta":540,"minecraft:dirt":2,"minecraft:bow":16,"minecraft:potion":42,"minecraft:stray_spawn_egg":5,"minecraft:tnt":1,"minecraft:nether_quartz_ore":6,"minecraft:stripped_oak_wood":3,"minecraft:smooth_red_sandstone":50,"minecraft:sandstone_slab":1098,"minecraft:blue_ice":14,"minecraft:light_gray_concrete_powder":108,"minecraft:coarse_dirt":2,"minecraft:acacia_planks":101,"minecraft:orange_terracotta":6,"minecraft:splash_potion":140,"minecraft:milk_bucket":8}},"DataVersion":1631}