{"stats":{"minecraft:used":{"minecraft:stone_bricks":2351,"minecraft:lapis_block":56,"minecraft:sign":2,"minecraft:tnt":3,"minecraft:redstone_torch":1},"minecraft:custom":{"minecraft:jump":116,"minecraft:time_since_rest":108814,"minecraft:crouch_one_cm":969,"minecraft:play_one_minute":108814,"minecraft:leave_game":1,"minecraft:sprint_one_cm":7219,"minecraft:time_since_death":108814,"minecraft:walk_one_cm":70753,"minecraft:sneak_time":493,"minecraft:drop":5,"minecraft:fly_one_cm":540679},"minecraft:dropped":{"minecraft:stone_bricks":4,"minecraft:carved_pumpkin":1}},"DataVersion":1631}