{"stats":{"minecraft:custom":{"minecraft:time_since_rest":439083,"minecraft:crouch_one_cm":10010,"minecraft:play_one_minute":439083,"minecraft:sprint_one_cm":17164,"minecraft:walk_one_cm":378900,"minecraft:sneak_time":13646,"minecraft:walk_under_water_one_cm":253589,"minecraft:jump":442,"minecraft:leave_game":9,"minecraft:walk_on_water_one_cm":79594,"minecraft:time_since_death":439083,"minecraft:swim_one_cm":90817,"minecraft:fly_one_cm":2711756},"minecraft:used":{"minecraft:stone_brick_stairs":10,"minecraft:dark_oak_planks":62,"minecraft:water_bucket":321,"minecraft:glowstone":28,"minecraft:rail":33,"minecraft:bricks":8,"minecraft:cobblestone_stairs":164,"minecraft:birch_planks":49,"minecraft:grass_block":114,"minecraft:jungle_planks":630,"minecraft:polished_andesite":407,"minecraft:brick_stairs":47,"minecraft:oak_planks":404,"minecraft:bucket":5,"minecraft:sponge":46,"minecraft:stone":799,"minecraft:acacia_planks":2,"minecraft:seagrass":2}},"DataVersion":1631}