{"stats":{"minecraft:dropped":{"minecraft:stone_sword":1,"minecraft:oak_planks":1,"minecraft:birch_planks":1,"minecraft:jungle_planks":2,"minecraft:polished_andesite":2},"minecraft:used":{"minecraft:oak_log":131,"minecraft:oak_planks":1064,"minecraft:sign":39,"minecraft:snowball":212,"minecraft:magenta_stained_glass":1,"minecraft:beacon":1,"minecraft:grass_block":238},"minecraft:custom":{"minecraft:jump":213,"minecraft:time_since_rest":158836,"minecraft:crouch_one_cm":384,"minecraft:play_one_minute":158836,"minecraft:leave_game":5,"minecraft:sprint_one_cm":27744,"minecraft:time_since_death":158836,"minecraft:walk_one_cm":170083,"minecraft:interact_with_beacon":2,"minecraft:sneak_time":251,"minecraft:drop":5,"minecraft:fly_one_cm":791305}},"DataVersion":1631}