{"stats":{"minecraft:dropped":{"minecraft:stone_axe":1,"minecraft:red_wool":8,"minecraft:stone_pickaxe":1,"minecraft:stone_sword":1,"minecraft:black_stained_glass":1,"minecraft:white_wool":8,"minecraft:wooden_axe":1,"minecraft:stone_shovel":1},"minecraft:custom":{"minecraft:time_since_rest":37318,"minecraft:crouch_one_cm":12516,"minecraft:play_one_minute":393074,"minecraft:sprint_one_cm":77276,"minecraft:walk_one_cm":436214,"minecraft:sneak_time":5690,"minecraft:drop":22,"minecraft:aviate_one_cm":278798,"minecraft:jump":1137,"minecraft:leave_game":8,"minecraft:time_since_death":393074,"minecraft:sleep_in_bed":2,"minecraft:fly_one_cm":1519332},"minecraft:used":{"minecraft:white_wool":5526,"minecraft:iron_bars":25,"minecraft:black_stained_glass":741,"minecraft:red_wool":2639,"minecraft:magenta_bed":1,"minecraft:quartz_slab":70,"minecraft:grass_block":1,"minecraft:iron_block":316,"minecraft:stone_button":1,"minecraft:gold_block":44,"minecraft:stone":13,"minecraft:gray_wool":370}},"DataVersion":1631}