{"stats":{"minecraft:crafted":{"minecraft:firework_star":32,"minecraft:firework_rocket":96},"minecraft:custom":{"minecraft:time_since_rest":217742,"minecraft:crouch_one_cm":3889,"minecraft:play_one_minute":217742,"minecraft:sprint_one_cm":6201,"minecraft:walk_one_cm":46941,"minecraft:sneak_time":13985,"minecraft:drop":3,"minecraft:aviate_one_cm":2215822,"minecraft:jump":218,"minecraft:leave_game":4,"minecraft:walk_on_water_one_cm":16,"minecraft:time_since_death":217742,"minecraft:interact_with_crafting_table":1,"minecraft:fly_one_cm":3450062},"minecraft:dropped":{"minecraft:stone_axe":1,"minecraft:stone_pickaxe":1,"minecraft:stone_shovel":1},"minecraft:used":{"minecraft:oak_log":1661,"minecraft:torch":72,"minecraft:water_bucket":5,"minecraft:cobblestone_stairs":5,"minecraft:firework_rocket":1,"minecraft:cobblestone":388,"minecraft:crafting_table":1,"minecraft:light_gray_concrete":51,"minecraft:birch_planks":2,"minecraft:dark_oak_fence":172,"minecraft:birch_wood":28,"minecraft:stone":283,"minecraft:birch_stairs":19,"minecraft:stripped_birch_wood":55,"minecraft:cobblestone_slab":361}},"DataVersion":1631}