{"stats":{"minecraft:used":{"minecraft:peony":6,"minecraft:sticky_piston":8,"minecraft:glass":6,"minecraft:piston":12,"minecraft:lever":24,"minecraft:water_bucket":252,"minecraft:end_rod":5,"minecraft:rose_bush":4,"minecraft:bricks":4224,"minecraft:spruce_door":11,"minecraft:brain_coral_fan":4,"minecraft:grass_block":736,"minecraft:armor_stand":27,"minecraft:pufferfish_spawn_egg":23,"minecraft:dispenser":1,"minecraft:redstone":63,"minecraft:brick_stairs":105,"minecraft:dead_brain_coral":6,"minecraft:black_carpet":196,"minecraft:silverfish_spawn_egg":2,"minecraft:ender_pearl":61,"minecraft:stone":400,"minecraft:brain_coral":3,"minecraft:torch":10,"minecraft:sand":798,"minecraft:potion":9,"minecraft:dirt":1641,"minecraft:anvil":3,"minecraft:bow":13,"minecraft:white_carpet":152,"minecraft:oak_sapling":3,"minecraft:tnt":12,"minecraft:white_banner":17,"minecraft:brick_slab":146,"minecraft:salmon_spawn_egg":39,"minecraft:glass_pane":315,"minecraft:drowned_spawn_egg":19,"minecraft:bucket":1,"minecraft:trapped_chest":2,"minecraft:cod_bucket":1,"minecraft:sea_pickle":3,"minecraft:salmon_bucket":2,"minecraft:note_block":4,"minecraft:lingering_potion":489,"minecraft:spruce_fence":72,"minecraft:turtle_egg":93,"minecraft:bone_meal":13},"minecraft:dropped":{"minecraft:sand":1,"minecraft:bow":1,"minecraft:grass_block":2,"minecraft:gold_ingot":64},"minecraft:custom":{"minecraft:time_since_rest":416700,"minecraft:sprint_one_cm":127967,"minecraft:walk_one_cm":899748,"minecraft:trigger_trapped_chest":1,"minecraft:drop":68,"minecraft:swim_one_cm":31878,"minecraft:tune_noteblock":18,"minecraft:fly_one_cm":1907528,"minecraft:open_chest":2,"minecraft:play_one_minute":416700,"minecraft:crouch_one_cm":1183,"minecraft:sneak_time":7037,"minecraft:walk_under_water_one_cm":91358,"minecraft:jump":1651,"minecraft:aviate_one_cm":183042,"minecraft:leave_game":13,"minecraft:walk_on_water_one_cm":26992,"minecraft:time_since_death":416700,"minecraft:climb_one_cm":9258,"minecraft:inspect_dispenser":3},"minecraft:picked_up":{"minecraft:white_carpet":1,"minecraft:lever":4,"minecraft:gold_ingot":96}},"DataVersion":1631}